{
	"configurations" : 
	[
		{
			"directories" : 
			[
				{
					"build" : ".",
					"jsonFile" : "directory-.-Debug-d0094a50bb2071803777.json",
					"minimumCMakeVersion" : 
					{
						"string" : "3.27"
					},
					"projectIndex" : 0,
					"source" : ".",
					"targetIndexes" : 
					[
						0
					]
				}
			],
			"name" : "Debug",
			"projects" : 
			[
				{
					"directoryIndexes" : 
					[
						0
					],
					"name" : "exame_modelo1",
					"targetIndexes" : 
					[
						0
					]
				}
			],
			"targets" : 
			[
				{
					"directoryIndex" : 0,
					"id" : "exame_modelo1::@6890427a1f51a3e7e1df",
					"jsonFile" : "target-exame_modelo1-Debug-3b6dacb9861490c391d8.json",
					"name" : "exame_modelo1",
					"projectIndex" : 0
				}
			]
		}
	],
	"kind" : "codemodel",
	"paths" : 
	{
		"build" : "D:/githubProjects/1parte_fp/exame_modelo1/cmake-build-debug",
		"source" : "D:/githubProjects/1parte_fp/exame_modelo1"
	},
	"version" : 
	{
		"major" : 2,
		"minor" : 6
	}
}
